_bp.cpython-36m-darwin.so
modbp/GenerateGraphs.py
modbp/HierarchicalBP.py
modbp/InferenceBP.py
modbp/ModularityBP.py
modbp/__init__.py
modbp/_version.py
modbp/bp.py
modbp/run_modbp_parallel.py
modbp-1.0.1.dist-info/LICENSE
modbp-1.0.1.dist-info/METADATA
modbp-1.0.1.dist-info/WHEEL
modbp-1.0.1.dist-info/top_level.txt
modbp-1.0.1.dist-info/RECORD
